[{"status": "VALID", "from": "CX", "to": "CE", "amount": 1781045, "time": "24/10/18 10:01:10", "block": 0}, {"status": "VALID", "from": "BP", "to": "AM", "amount": 4604777, "time": "24/10/18 10:02:04", "block": 0}, {"status": "VALID", "from": "M", "to": "H", "amount": 1225048, "time": "24/10/18 10:03:47", "block": 0}, {"status": "VALID", "from": "CM", "to": "G", "amount": 414625, "time": "24/10/18 10:04:40", "block": 0}, {"status": "VALID", "from": "D", "to": "L", "amount": 14891634, "time": "24/10/18 10:05:48", "block": 0}, {"status": "UNRECORDED", "from": "J", "to": "DE", "amount": 21706549, "time": "24/10/18 10:06:20", "block": 0}, {"status": "VALID", "from": "W", "to": "BJ", "amount": 5952158, "time": "24/10/18 10:06:35", "block": 0}, {"status": "VALID", "from": "BM", "to": "CA", "amount": 6521753, "time": "24/10/18 10:07:58", "block": 0}, {"status": "VALID", "from": "BF", "to": "M", "amount": 3714008, "time": "24/10/18 10:08:28", "block": 0}, {"status": "VALID", "from": "BQ", "to": "DB", "amount": 4937172, "time": "24/10/18 10:09:51", "block": 0}, {"status": "VALID", "from": "R", "to": "A", "amount": 2242921, "time": "24/10/18 10:10:47", "block": 0}, {"status": "VALID", "from": "AA", "to": "CJ", "amount": 10012174, "time": "24/10/18 10:11:40", "block": 0}, {"status": "VALID", "from": "AU", "to": "BQ", "amount": 7240950, "time": "24/10/18 10:12:42", "block": 0}, {"status": "INVALID", "from": "BX", "to": "CD", "amount": 837065, "time": "24/10/18 10:12:57", "block": -1}, {"status": "VALID", "from": "AE", "to": "BP", "amount": 3058640, "time": "24/10/18 10:13:04", "block": 0}, {"status": "VALID", "from": "B", "to": "CC", "amount": 10707758, "time": "24/10/18 10:13:33", "block": 0}, {"status": "VALID", "from": "DA", "to": "I", "amount": 109749, "time": "24/10/18 10:13:51", "block": 0}, {"status": "INVALID", "from": "BK", "to": "Z", "amount": 1491820, "time": "24/10/18 10:14:09", "block": -1}, {"status": "VALID", "from": "AC", "to": "DA", "amount": 5827202, "time": "24/10/18 10:16:07", "block": 0}, {"status": "VALID", "from": "CN", "to": "U", "amount": 1430599, "time": "24/10/18 10:16:34", "block": 0}, {"status": "VALID", "from": "CZ", "to": "AA", "amount": 1872291, "time": "24/10/18 10:16:54", "block": 20}, {"status": "INVALID", "from": "AF", "to": "BM", "amount": 5127308, "time": "24/10/18 10:17:56", "block": -1}, {"status": "VALID", "from": "BV", "to": "BO", "amount": 2870365, "time": "24/10/18 10:18:07", "block": 20}, {"status": "VALID", "from": "B", "to": "AJ", "amount": 4472554, "time": "24/10/18 10:20:05", "block": 20}, {"status": "VALID", "from": "CR", "to": "BU", "amount": 2688687, "time": "24/10/18 10:21:05", "block": 20}, {"status": "INVALID", "from": "AS", "to": "AI", "amount": 4317031, "time": "24/10/18 10:22:26", "block": -1}, {"status": "UNRECORDED", "from": "BG", "to": "AY", "amount": 6019502, "time": "24/10/18 10:24:54", "block": 20}, {"status": "VALID", "from": "BU", "to": "CR", "amount": 8146283, "time": "24/10/18 10:26:54", "block": 20}, {"status": "UNRECORDED", "from": "J", "to": "BS", "amount": 27877364, "time": "24/10/18 10:28:25", "block": 20}, {"status": "VALID", "from": "C", "to": "CB", "amount": 1991381, "time": "24/10/18 10:28:47", "block": 20}, {"status": "VALID", "from": "AJ", "to": "CE", "amount": 9392688, "time": "24/10/18 10:33:19", "block": 20}, {"status": "VALID", "from": "CK", "to": "BD", "amount": 1813173, "time": "24/10/18 10:33:38", "block": 20}, {"status": "VALID", "from": "N", "to": "A", "amount": 14585843, "time": "24/10/18 10:37:43", "block": 20}, {"status": "INVALID", "from": "BP", "to": "H", "amount": 1618797, "time": "24/10/18 10:38:03", "block": -1}, {"status": "VALID", "from": "CB", "to": "AL", "amount": 4354464, "time": "24/10/18 10:38:11", "block": 20}, {"status": "VALID", "from": "CY", "to": "W", "amount": 440248, "time": "24/10/18 10:42:00", "block": 20}, {"status": "VALID", "from": "AP", "to": "AI", "amount": 4410231, "time": "24/10/18 10:42:17", "block": 20}, {"status": "VALID", "from": "AD", "to": "AB", "amount": 537615, "time": "24/10/18 10:44:30", "block": 20}, {"status": "VALID", "from": "BX", "to": "S", "amount": 4446881, "time": "24/10/18 10:44:30", "block": 20}, {"status": "VALID", "from": "AB", "to": "CX", "amount": 920752, "time": "24/10/18 10:47:10", "block": 20}, {"status": "VALID", "from": "CJ", "to": "B", "amount": 1155554, "time": "24/10/18 10:48:36", "block": 40}, {"status": "UNRECORDED", "from": "AV", "to": "CQ", "amount": 1003041, "time": "24/10/18 10:49:52", "block": 40}, {"status": "VALID", "from": "J", "to": "BK", "amount": 21690799, "time": "24/10/18 10:50:13", "block": 40}, {"status": "VALID", "from": "BJ", "to": "AX", "amount": 889088, "time": "24/10/18 10:50:14", "block": 40}, {"status": "VALID", "from": "AC", "to": "CI", "amount": 1476547, "time": "24/10/18 10:55:39", "block": 40}, {"status": "VALID", "from": "N", "to": "A", "amount": 6453933, "time": "24/10/18 10:57:04", "block": 40}, {"status": "INVALID", "from": "BW", "to": "K", "amount": 4862432, "time": "24/10/18 10:58:47", "block": -1}, {"status": "INVALID", "from": "BB", "to": "BX", "amount": 1619824, "time": "24/10/18 10:59:38", "block": -1}, {"status": "VALID", "from": "BX", "to": "BP", "amount": 111537, "time": "24/10/18 11:00:33", "block": 40}, {"status": "VALID", "from": "CT", "to": "CS", "amount": 1267309, "time": "24/10/18 11:00:46", "block": 40}, {"status": "VALID", "from": "BV", "to": "AJ", "amount": 1118308, "time": "24/10/18 11:00:49", "block": 40}, {"status": "UNRECORDED", "from": "AZ", "to": "BP", "amount": 3314989, "time": "24/10/18 11:01:24", "block": 40}, {"status": "VALID", "from": "AF", "to": "J", "amount": 877788, "time": "24/10/18 11:01:24", "block": 40}, {"status": "VALID", "from": "S", "to": "E", "amount": 18251410, "time": "24/10/18 11:02:46", "block": 40}, {"status": "VALID", "from": "V", "to": "CJ", "amount": 8701669, "time": "24/10/18 11:03:16", "block": 40}, {"status": "UNRECORDED", "from": "E", "to": "Y", "amount": 31035560, "time": "24/10/18 11:03:40", "block": 40}, {"status": "VALID", "from": "CH", "to": "AE", "amount": 1693639, "time": "24/10/18 11:05:34", "block": 40}, {"status": "VALID", "from": "CQ", "to": "CR", "amount": 2207778, "time": "24/10/18 11:05:50", "block": 40}, {"status": "INVALID", "from": "CS", "to": "E", "amount": 4226845, "time": "24/10/18 11:06:40", "block": -1}, {"status": "INVALID", "from": "H", "to": "DA", "amount": 17144122, "time": "24/10/18 11:08:28", "block": -1}, {"status": "VALID", "from": "CU", "to": "P", "amount": 1341419, "time": "24/10/18 11:08:47", "block": 60}, {"status": "VALID", "from": "AL", "to": "T", "amount": 10401105, "time": "24/10/18 11:08:48", "block": 60}, {"status": "UNRECORDED", "from": "BC", "to": "R", "amount": 3466775, "time": "24/10/18 11:08:52", "block": 60}, {"status": "INVALID", "from": "AX", "to": "BT", "amount": 7992743, "time": "24/10/18 11:10:05", "block": -1}, {"status": "INVALID", "from": "I", "to": "Q", "amount": 5570687, "time": "24/10/18 11:10:31", "block": -1}, {"status": "VALID", "from": "AR", "to": "B", "amount": 4675211, "time": "24/10/18 11:11:53", "block": 60}, {"status": "VALID", "from": "CJ", "to": "BD", "amount": 107604, "time": "24/10/18 11:13:03", "block": 60}, {"status": "INVALID", "from": "CT", "to": "CE", "amount": 648182, "time": "24/10/18 11:13:12", "block": -1}, {"status": "VALID", "from": "BV", "to": "AE", "amount": 883280, "time": "24/10/18 11:16:24", "block": 60}, {"status": "VALID", "from": "BR", "to": "CT", "amount": 6481693, "time": "24/10/18 11:16:53", "block": 60}, {"status": "VALID", "from": "BB", "to": "AO", "amount": 3906766, "time": "24/10/18 11:17:53", "block": 60}, {"status": "VALID", "from": "AZ", "to": "AN", "amount": 7637361, "time": "24/10/18 11:18:37", "block": 60}, {"status": "INVALID", "from": "CF", "to": "V", "amount": 163518, "time": "24/10/18 11:19:03", "block": -1}, {"status": "VALID", "from": "CE", "to": "BH", "amount": 12765698, "time": "24/10/18 11:19:27", "block": 60}, {"status": "VALID", "from": "CI", "to": "AP", "amount": 1284334, "time": "24/10/18 11:20:10", "block": 60}, {"status": "INVALID", "from": "DC", "to": "AT", "amount": 238017, "time": "24/10/18 11:20:31", "block": -1}, {"status": "VALID", "from": "H", "to": "BH", "amount": 2561946, "time": "24/10/18 11:21:49", "block": 60}, {"status": "VALID", "from": "AW", "to": "CA", "amount": 6881562, "time": "24/10/18 11:23:15", "block": 60}, {"status": "VALID", "from": "BH", "to": "DE", "amount": 20157176, "time": "24/10/18 11:23:22", "block": 60}, {"status": "VALID", "from": "DD", "to": "BR", "amount": 723199, "time": "24/10/18 11:24:52", "block": 60}, {"status": "INVALID", "from": "AB", "to": "BJ", "amount": 953438, "time": "24/10/18 11:25:10", "block": -1}, {"status": "INVALID", "from": "BY", "to": "AY", "amount": 1968866, "time": "24/10/18 11:27:08", "block": -1}, {"status": "VALID", "from": "CW", "to": "DA", "amount": 1292117, "time": "24/10/18 11:27:42", "block": 80}, {"status": "INVALID", "from": "G", "to": "BN", "amount": 556864, "time": "24/10/18 11:28:02", "block": -1}, {"status": "VALID", "from": "CC", "to": "CV", "amount": 8834251, "time": "24/10/18 11:28:27", "block": 80}, {"status": "VALID", "from": "DE", "to": "BM", "amount": 9869901, "time": "24/10/18 11:28:28", "block": 80}, {"status": "INVALID", "from": "L", "to": "V", "amount": 43648607, "time": "24/10/18 11:32:59", "block": -1}, {"status": "VALID", "from": "BS", "to": "BX", "amount": 3373781, "time": "24/10/18 11:33:42", "block": 80}, {"status": "VALID", "from": "T", "to": "AR", "amount": 18195698, "time": "24/10/18 11:33:43", "block": 80}, {"status": "VALID", "from": "AM", "to": "T", "amount": 9055970, "time": "24/10/18 11:35:25", "block": 80}, {"status": "UNRECORDED", "from": "Z", "to": "F", "amount": 5442488, "time": "24/10/18 11:41:43", "block": 80}, {"status": "INVALID", "from": "AL", "to": "K", "amount": 115445, "time": "24/10/18 11:42:05", "block": -1}, {"status": "INVALID", "from": "AY", "to": "H", "amount": 5511502, "time": "24/10/18 11:44:01", "block": -1}, {"status": "VALID", "from": "X", "to": "K", "amount": 772846, "time": "24/10/18 11:45:05", "block": 80}, {"status": "VALID", "from": "BE", "to": "CN", "amount": 5063376, "time": "24/10/18 11:45:10", "block": 80}, {"status": "VALID", "from": "AH", "to": "AY", "amount": 5742626, "time": "24/10/18 11:45:12", "block": 80}, {"status": "VALID", "from": "BG", "to": "BR", "amount": 4948567, "time": "24/10/18 11:45:51", "block": 80}, {"status": "INVALID", "from": "CA", "to": "CU", "amount": 2623202, "time": "24/10/18 11:46:00", "block": -1}, {"status": "INVALID", "from": "CN", "to": "BS", "amount": 1747283, "time": "24/10/18 11:47:37", "block": -1}, {"status": "VALID", "from": "AV", "to": "DB", "amount": 3979397, "time": "24/10/18 11:48:24", "block": 80}, {"status": "INVALID", "from": "CV", "to": "BN", "amount": 4302013, "time": "24/10/18 11:48:35", "block": -1}, {"status": "VALID", "from": "S", "to": "BV", "amount": 1470514, "time": "24/10/18 11:48:58", "block": 100}, {"status": "UNRECORDED", "from": "DD", "to": "AU", "amount": 941077, "time": "24/10/18 11:50:00", "block": 100}, {"status": "VALID", "from": "K", "to": "N", "amount": 27083489, "time": "24/10/18 11:50:01", "block": 100}, {"status": "UNRECORDED", "from": "L", "to": "CT", "amount": 16189065, "time": "24/10/18 11:50:07", "block": 100}, {"status": "VALID", "from": "Q", "to": "R", "amount": 408952, "time": "24/10/18 11:51:30", "block": 100}, {"status": "VALID", "from": "AO", "to": "DB", "amount": 11341954, "time": "24/10/18 11:52:05", "block": 100}, {"status": "VALID", "from": "BE", "to": "BO", "amount": 1659118, "time": "24/10/18 11:52:39", "block": 100}, {"status": "VALID", "from": "AV", "to": "BR", "amount": 1413537, "time": "24/10/18 11:54:37", "block": 100}, {"status": "INVALID", "from": "CE", "to": "CV", "amount": 1181150, "time": "24/10/18 11:55:26", "block": -1}, {"status": "INVALID", "from": "V", "to": "CO", "amount": 725060, "time": "24/10/18 11:57:44", "block": -1}, {"status": "VALID", "from": "CI", "to": "BY", "amount": 319070, "time": "24/10/18 11:58:27", "block": 100}, {"status": "VALID", "from": "DC", "to": "AJ", "amount": 1385093, "time": "24/10/18 11:59:52", "block": 100}, {"status": "VALID", "from": "CC", "to": "CV", "amount": 170173, "time": "24/10/18 12:00:57", "block": 100}, {"status": "UNRECORDED", "from": "CH", "to": "AV", "amount": 1445815, "time": "24/10/18 12:01:11", "block": 100}, {"status": "VALID", "from": "BX", "to": "H", "amount": 2198966, "time": "24/10/18 12:01:37", "block": 100}, {"status": "VALID", "from": "CN", "to": "L", "amount": 6260774, "time": "24/10/18 12:01:41", "block": 100}, {"status": "VALID", "from": "BA", "to": "CK", "amount": 6956023, "time": "24/10/18 12:03:20", "block": 100}, {"status": "INVALID", "from": "AA", "to": "CD", "amount": 2170309, "time": "24/10/18 12:03:47", "block": -1}, {"status": "VALID", "from": "CG", "to": "BZ", "amount": 2151133, "time": "24/10/18 12:04:06", "block": 100}, {"status": "INVALID", "from": "AW", "to": "AT", "amount": 389252, "time": "24/10/18 12:04:16", "block": -1}, {"status": "VALID", "from": "N", "to": "P", "amount": 853689, "time": "24/10/18 12:04:18", "block": 120}, {"status": "VALID", "from": "DD", "to": "AD", "amount": 64905, "time": "24/10/18 12:08:01", "block": 120}, {"status": "VALID", "from": "BK", "to": "BS", "amount": 14731626, "time": "24/10/18 12:08:05", "block": 120}, {"status": "VALID", "from": "AX", "to": "AN", "amount": 6007599, "time": "24/10/18 12:10:12", "block": 120}, {"status": "INVALID", "from": "AD", "to": "CL", "amount": 937970, "time": "24/10/18 12:10:27", "block": -1}, {"status": "VALID", "from": "CB", "to": "D", "amount": 982323, "time": "24/10/18 12:10:31", "block": 120}, {"status": "UNRECORDED", "from": "CN", "to": "CZ", "amount": 384665, "time": "24/10/18 12:14:16", "block": 120}, {"status": "VALID", "from": "AH", "to": "AD", "amount": 1363899, "time": "24/10/18 12:15:08", "block": 120}, {"status": "INVALID", "from": "G", "to": "CW", "amount": 2559485, "time": "24/10/18 12:15:16", "block": -1}, {"status": "VALID", "from": "AS", "to": "K", "amount": 5507306, "time": "24/10/18 12:18:45", "block": 120}, {"status": "INVALID", "from": "Y", "to": "BQ", "amount": 10101051, "time": "24/10/18 12:18:51", "block": -1}, {"status": "VALID", "from": "BM", "to": "CS", "amount": 3065834, "time": "24/10/18 12:19:22", "block": 120}, {"status": "VALID", "from": "BZ", "to": "BA", "amount": 3314055, "time": "24/10/18 12:20:05", "block": 120}, {"status": "INVALID", "from": "CR", "to": "AF", "amount": 1483193, "time": "24/10/18 12:20:45", "block": -1}, {"status": "VALID", "from": "AU", "to": "CK", "amount": 247276, "time": "24/10/18 12:20:48", "block": 120}, {"status": "VALID", "from": "Q", "to": "CB", "amount": 12358067, "time": "24/10/18 12:21:06", "block": 120}, {"status": "VALID", "from": "BD", "to": "CM", "amount": 8805087, "time": "24/10/18 12:23:26", "block": 120}, {"status": "VALID", "from": "DC", "to": "AE", "amount": 543210, "time": "24/10/18 12:24:21", "block": 120}, {"status": "VALID", "from": "L", "to": "CO", "amount": 44248049, "time": "24/10/18 12:24:41", "block": 120}, {"status": "UNRECORDED", "from": "U", "to": "CV", "amount": 13306821, "time": "24/10/18 12:25:48", "block": 140}, {"status": "UNRECORDED", "from": "CR", "to": "AA", "amount": 4483357, "time": "24/10/18 12:26:26", "block": 140}, {"status": "INVALID", "from": "CW", "to": "CL", "amount": 176921, "time": "24/10/18 12:27:37", "block": -1}, {"status": "INVALID", "from": "D", "to": "AM", "amount": 5931613, "time": "24/10/18 12:29:39", "block": -1}, {"status": "VALID", "from": "AW", "to": "AL", "amount": 1081137, "time": "24/10/18 12:29:53", "block": 140}, {"status": "INVALID", "from": "AK", "to": "I", "amount": 8230415, "time": "24/10/18 12:30:13", "block": -1}, {"status": "VALID", "from": "M", "to": "CN", "amount": 28723150, "time": "24/10/18 12:30:48", "block": 140}, {"status": "VALID", "from": "DD", "to": "K", "amount": 180255, "time": "24/10/18 12:31:04", "block": 140}, {"status": "INVALID", "from": "R", "to": "DC", "amount": 13720895, "time": "24/10/18 12:32:47", "block": -1}, {"status": "VALID", "from": "BY", "to": "BN", "amount": 3035220, "time": "24/10/18 12:33:26", "block": 140}, {"status": "VALID", "from": "CG", "to": "E", "amount": 307003, "time": "24/10/18 12:33:50", "block": 140}, {"status": "VALID", "from": "W", "to": "BD", "amount": 6354338, "time": "24/10/18 12:34:42", "block": 140}, {"status": "INVALID", "from": "AD", "to": "CC", "amount": 2671556, "time": "24/10/18 12:36:00", "block": -1}, {"status": "VALID", "from": "T", "to": "CL", "amount": 2594926, "time": "24/10/18 12:36:33", "block": 140}, {"status": "VALID", "from": "BA", "to": "S", "amount": 531954, "time": "24/10/18 12:37:34", "block": 140}, {"status": "VALID", "from": "AE", "to": "CB", "amount": 5154567, "time": "24/10/18 12:39:54", "block": 140}, {"status": "VALID", "from": "AT", "to": "BS", "amount": 642297, "time": "24/10/18 12:40:12", "block": 140}, {"status": "VALID", "from": "DA", "to": "BX", "amount": 2206715, "time": "24/10/18 12:40:57", "block": 140}, {"status": "INVALID", "from": "CJ", "to": "W", "amount": 10212739, "time": "24/10/18 12:41:48", "block": -1}, {"status": "VALID", "from": "CC", "to": "BI", "amount": 1090923, "time": "24/10/18 12:41:49", "block": 140}, {"status": "VALID", "from": "AI", "to": "DC", "amount": 495110, "time": "24/10/18 12:42:28", "block": 160}, {"status": "INVALID", "from": "AW", "to": "BW", "amount": 62545, "time": "24/10/18 12:43:49", "block": -1}, {"status": "VALID", "from": "BL", "to": "BD", "amount": 103350, "time": "24/10/18 12:44:23", "block": 160}, {"status": "VALID", "from": "F", "to": "CT", "amount": 40907786, "time": "24/10/18 12:45:56", "block": 160}, {"status": "VALID", "from": "BO", "to": "AG", "amount": 9726974, "time": "24/10/18 12:46:38", "block": 160}, {"status": "VALID", "from": "CS", "to": "AD", "amount": 6063668, "time": "24/10/18 12:47:25", "block": 160}, {"status": "VALID", "from": "AE", "to": "CA", "amount": 2066346, "time": "24/10/18 12:48:20", "block": 160}, {"status": "INVALID", "from": "AZ", "to": "CB", "amount": 470268, "time": "24/10/18 12:48:43", "block": -1}, {"status": "VALID", "from": "H", "to": "BP", "amount": 6092093, "time": "24/10/18 12:50:11", "block": 160}, {"status": "VALID", "from": "DB", "to": "CZ", "amount": 22068037, "time": "24/10/18 12:51:04", "block": 160}, {"status": "VALID", "from": "CT", "to": "AZ", "amount": 48636118, "time": "24/10/18 12:53:38", "block": 160}, {"status": "VALID", "from": "S", "to": "X", "amount": 500435, "time": "24/10/18 12:53:45", "block": 160}, {"status": "VALID", "from": "K", "to": "AP", "amount": 17899280, "time": "24/10/18 12:53:52", "block": 160}, {"status": "VALID", "from": "M", "to": "AD", "amount": 3122996, "time": "24/10/18 12:55:04", "block": 160}, {"status": "VALID", "from": "C", "to": "CK", "amount": 4480548, "time": "24/10/18 12:55:19", "block": 160}, {"status": "INVALID", "from": "DC", "to": "AN", "amount": 399123, "time": "24/10/18 12:55:27", "block": -1}, {"status": "UNRECORDED", "from": "DA", "to": "BK", "amount": 5770294, "time": "24/10/18 12:56:45", "block": 160}, {"status": "VALID", "from": "CZ", "to": "BM", "amount": 13999497, "time": "24/10/18 12:57:18", "block": 160}, {"status": "UNRECORDED", "from": "DE", "to": "V", "amount": 1733348, "time": "24/10/18 12:59:05", "block": 160}, {"status": "VALID", "from": "AA", "to": "CP", "amount": 837755, "time": "24/10/18 13:00:34", "block": 160}, {"status": "VALID", "from": "AC", "to": "CM", "amount": 1397971, "time": "24/10/18 13:01:57", "block": 180}, {"status": "VALID", "from": "BU", "to": "CR", "amount": 270072, "time": "24/10/18 13:02:15", "block": 180}, {"status": "INVALID", "from": "BE", "to": "X", "amount": 634061, "time": "24/10/18 13:02:42", "block": -1}, {"status": "VALID", "from": "S", "to": "CH", "amount": 528457, "time": "24/10/18 13:03:00", "block": 180}, {"status": "VALID", "from": "AX", "to": "L", "amount": 3073955, "time": "24/10/18 13:03:21", "block": 180}, {"status": "UNRECORDED", "from": "W", "to": "CX", "amount": 9472, "time": "24/10/18 13:03:31", "block": 180}, {"status": "VALID", "from": "Z", "to": "CZ", "amount": 7159953, "time": "24/10/18 13:05:25", "block": 180}, {"status": "VALID", "from": "CC", "to": "O", "amount": 5043325, "time": "24/10/18 13:06:40", "block": 180}, {"status": "VALID", "from": "AF", "to": "AP", "amount": 7366316, "time": "24/10/18 13:07:14", "block": 180}, {"status": "INVALID", "from": "X", "to": "AU", "amount": 251990, "time": "24/10/18 13:07:47", "block": -1}, {"status": "VALID", "from": "CJ", "to": "BQ", "amount": 7176031, "time": "24/10/18 13:08:06", "block": 180}, {"status": "INVALID", "from": "CO", "to": "D", "amount": 15292094, "time": "24/10/18 13:12:38", "block": -1}, {"status": "VALID", "from": "CP", "to": "BP", "amount": 1144221, "time": "24/10/18 13:12:42", "block": 180}, {"status": "UNRECORDED", "from": "C", "to": "AH", "amount": 1442489, "time": "24/10/18 13:15:36", "block": 180}, {"status": "VALID", "from": "BC", "to": "J", "amount": 2379953, "time": "24/10/18 13:15:40", "block": 180}, {"status": "UNRECORDED", "from": "CZ", "to": "AJ", "amount": 12329516, "time": "24/10/18 13:16:35", "block": 180}, {"status": "VALID", "from": "P", "to": "CK", "amount": 8406611, "time": "24/10/18 13:16:47", "block": 180}, {"status": "VALID", "from": "M", "to": "BF", "amount": 1252280, "time": "24/10/18 13:19:01", "block": 180}, {"status": "INVALID", "from": "DA", "to": "AH", "amount": 280206, "time": "24/10/18 13:19:26", "block": -1}, {"status": "VALID", "from": "CL", "to": "BA", "amount": 2381665, "time": "24/10/18 13:21:21", "block": 180}, {"status": "VALID", "from": "CD", "to": "CF", "amount": 3039265, "time": "24/10/18 13:21:58", "block": 200}, {"status": "VALID", "from": "AY", "to": "AU", "amount": 13597263, "time": "24/10/18 13:22:47", "block": 200}, {"status": "INVALID", "from": "AW", "to": "CU", "amount": 138335, "time": "24/10/18 13:22:56", "block": -1}, {"status": "VALID", "from": "M", "to": "BQ", "amount": 3199164, "time": "24/10/18 13:26:05", "block": 200}, {"status": "VALID", "from": "Q", "to": "CD", "amount": 2828455, "time": "24/10/18 13:26:26", "block": 200}, {"status": "VALID", "from": "CM", "to": "BU", "amount": 9176521, "time": "24/10/18 13:27:10", "block": 200}, {"status": "VALID", "from": "CB", "to": "CM", "amount": 16534304, "time": "24/10/18 13:28:18", "block": 200}, {"status": "VALID", "from": "AX", "to": "BV", "amount": 28086, "time": "24/10/18 13:29:37", "block": 200}, {"status": "VALID", "from": "CO", "to": "DD", "amount": 45477644, "time": "24/10/18 13:30:11", "block": 200}, {"status": "VALID", "from": "H", "to": "E", "amount": 5668757, "time": "24/10/18 13:30:15", "block": 200}, {"status": "VALID", "from": "AL", "to": "BS", "amount": 1968437, "time": "24/10/18 13:30:40", "block": 200}, {"status": "VALID", "from": "BS", "to": "P", "amount": 3913991, "time": "24/10/18 13:30:45", "block": 200}, {"status": "UNRECORDED", "from": "AB", "to": "BE", "amount": 3115070, "time": "24/10/18 13:30:46", "block": 200}, {"status": "INVALID", "from": "AQ", "to": "CN", "amount": 4032746, "time": "24/10/18 13:34:04", "block": -1}, {"status": "INVALID", "from": "CT", "to": "BE", "amount": 5185, "time": "24/10/18 13:35:25", "block": -1}, {"status": "VALID", "from": "AI", "to": "B", "amount": 7129930, "time": "24/10/18 13:35:26", "block": 200}, {"status": "UNRECORDED", "from": "BP", "to": "BH", "amount": 10582501, "time": "24/10/18 13:36:05", "block": 200}, {"status": "VALID", "from": "BH", "to": "BJ", "amount": 1769911, "time": "24/10/18 13:36:45", "block": 200}, {"status": "VALID", "from": "AG", "to": "DB", "amount": 13608423, "time": "24/10/18 13:37:15", "block": 200}, {"status": "VALID", "from": "O", "to": "BV", "amount": 13676450, "time": "24/10/18 13:38:04", "block": 200}, {"status": "UNRECORDED", "from": "R", "to": "Y", "amount": 3390052, "time": "24/10/18 13:39:21", "block": 220}, {"status": "VALID", "from": "DD", "to": "G", "amount": 41493049, "time": "24/10/18 13:39:49", "block": 220}, {"status": "INVALID", "from": "D", "to": "AV", "amount": 3191642, "time": "24/10/18 13:40:05", "block": -1}, {"status": "UNRECORDED", "from": "BU", "to": "BP", "amount": 711441, "time": "24/10/18 13:40:29", "block": 220}, {"status": "VALID", "from": "BE", "to": "CC", "amount": 144774, "time": "24/10/18 13:41:00", "block": 220}, {"status": "UNRECORDED", "from": "CZ", "to": "Z", "amount": 5673386, "time": "24/10/18 13:41:25", "block": 220}, {"status": "INVALID", "from": "G", "to": "C", "amount": 42954412, "time": "24/10/18 13:41:28", "block": -1}, {"status": "INVALID", "from": "AJ", "to": "CX", "amount": 5788097, "time": "24/10/18 13:41:47", "block": -1}, {"status": "VALID", "from": "BT", "to": "CQ", "amount": 3068141, "time": "24/10/18 13:42:45", "block": 220}, {"status": "UNRECORDED", "from": "C", "to": "AQ", "amount": 1328062, "time": "24/10/18 13:43:16", "block": 220}, {"status": "VALID", "from": "CA", "to": "AH", "amount": 15008218, "time": "24/10/18 13:43:24", "block": 220}, {"status": "VALID", "from": "CB", "to": "BF", "amount": 20147, "time": "24/10/18 13:45:31", "block": 220}, {"status": "VALID", "from": "CI", "to": "CC", "amount": 1636928, "time": "24/10/18 13:47:20", "block": 220}, {"status": "VALID", "from": "CT", "to": "BL", "amount": 88447, "time": "24/10/18 13:51:24", "block": 220}, {"status": "INVALID", "from": "AY", "to": "BN", "amount": 243153, "time": "24/10/18 13:51:48", "block": -1}, {"status": "UNRECORDED", "from": "L", "to": "CF", "amount": 14819397, "time": "24/10/18 13:53:11", "block": 220}, {"status": "VALID", "from": "BX", "to": "CO", "amount": 1130263, "time": "24/10/18 13:53:34", "block": 220}, {"status": "VALID", "from": "CQ", "to": "AP", "amount": 2871800, "time": "24/10/18 13:56:52", "block": 220}, {"status": "VALID", "from": "AT", "to": "AJ", "amount": 3360806, "time": "24/10/18 13:59:37", "block": 220}, {"status": "VALID", "from": "A", "to": "DB", "amount": 5976485, "time": "24/10/18 14:00:11", "block": 220}, {"status": "VALID", "from": "CP", "to": "BM", "amount": 1181213, "time": "24/10/18 14:01:14", "block": 240}, {"status": "VALID", "from": "CU", "to": "BF", "amount": 1400987, "time": "24/10/18 14:02:00", "block": 240}, {"status": "INVALID", "from": "AT", "to": "CE", "amount": 2161279, "time": "24/10/18 14:02:40", "block": -1}, {"status": "VALID", "from": "DE", "to": "AH", "amount": 8491094, "time": "24/10/18 14:03:09", "block": 240}, {"status": "VALID", "from": "CN", "to": "BL", "amount": 1498590, "time": "24/10/18 14:03:32", "block": 240}, {"status": "VALID", "from": "BL", "to": "M", "amount": 7761023, "time": "24/10/18 14:04:15", "block": 240}, {"status": "INVALID", "from": "V", "to": "BQ", "amount": 2725578, "time": "24/10/18 14:05:27", "block": -1}, {"status": "VALID", "from": "CJ", "to": "CA", "amount": 3643774, "time": "24/10/18 14:06:10", "block": 240}, {"status": "VALID", "from": "H", "to": "AW", "amount": 729871, "time": "24/10/18 14:09:11", "block": 240}, {"status": "VALID", "from": "G", "to": "DD", "amount": 21740955, "time": "24/10/18 14:10:33", "block": 240}, {"status": "VALID", "from": "AG", "to": "BA", "amount": 1432572, "time": "24/10/18 14:11:51", "block": 240}, {"status": "INVALID", "from": "CQ", "to": "BB", "amount": 185444, "time": "24/10/18 14:12:05", "block": -1}, {"status": "VALID", "from": "BW", "to": "CM", "amount": 3043322, "time": "24/10/18 14:12:15", "block": 240}, {"status": "VALID", "from": "AD", "to": "CW", "amount": 268029, "time": "24/10/18 14:12:51", "block": 240}, {"status": "INVALID", "from": "AP", "to": "BW", "amount": 30473103, "time": "24/10/18 14:12:59", "block": -1}, {"status": "VALID", "from": "B", "to": "BS", "amount": 9499949, "time": "24/10/18 14:13:01", "block": 240}, {"status": "VALID", "from": "BV", "to": "CG", "amount": 2068986, "time": "24/10/18 14:14:43", "block": 240}, {"status": "VALID", "from": "AJ", "to": "X", "amount": 3609589, "time": "24/10/18 14:14:49", "block": 240}, {"status": "VALID", "from": "CM", "to": "B", "amount": 9700056, "time": "24/10/18 14:14:54", "block": 240}, {"status": "VALID", "from": "BB", "to": "AR", "amount": 2266139, "time": "24/10/18 14:15:04", "block": 240}, {"status": "VALID", "from": "CQ", "to": "BW", "amount": 996822, "time": "24/10/18 14:15:35", "block": 260}, {"status": "VALID", "from": "AT", "to": "CS", "amount": 3806845, "time": "24/10/18 14:20:03", "block": 260}, {"status": "VALID", "from": "AQ", "to": "Q", "amount": 6314124, "time": "24/10/18 14:20:59", "block": 260}, {"status": "VALID", "from": "AF", "to": "AL", "amount": 143713, "time": "24/10/18 14:21:04", "block": 260}, {"status": "VALID", "from": "CN", "to": "BD", "amount": 11290553, "time": "24/10/18 14:22:13", "block": 260}, {"status": "VALID", "from": "BN", "to": "BV", "amount": 4088992, "time": "24/10/18 14:22:55", "block": 260}, {"status": "VALID", "from": "BB", "to": "CH", "amount": 487040, "time": "24/10/18 14:23:47", "block": 260}, {"status": "VALID", "from": "CT", "to": "AJ", "amount": 59230, "time": "24/10/18 14:24:43", "block": 260}, {"status": "VALID", "from": "AX", "to": "AJ", "amount": 87214, "time": "24/10/18 14:24:51", "block": 260}, {"status": "INVALID", "from": "O", "to": "CI", "amount": 1731783, "time": "24/10/18 14:26:22", "block": -1}, {"status": "VALID", "from": "CA", "to": "BM", "amount": 6833673, "time": "24/10/18 14:27:49", "block": 260}, {"status": "INVALID", "from": "BF", "to": "BV", "amount": 2394633, "time": "24/10/18 14:27:53", "block": -1}, {"status": "VALID", "from": "DB", "to": "CR", "amount": 12058867, "time": "24/10/18 14:28:29", "block": 260}, {"status": "VALID", "from": "DC", "to": "CO", "amount": 88568, "time": "24/10/18 14:28:50", "block": 260}, {"status": "VALID", "from": "S", "to": "AG", "amount": 167337, "time": "24/10/18 14:34:14", "block": 260}, {"status": "VALID", "from": "N", "to": "BX", "amount": 28818162, "time": "24/10/18 14:34:40", "block": 260}, {"status": "VALID", "from": "K", "to": "CK", "amount": 6602649, "time": "24/10/18 14:34:50", "block": 260}, {"status": "INVALID", "from": "AS", "to": "Q", "amount": 166609, "time": "24/10/18 14:36:47", "block": -1}, {"status": "INVALID", "from": "R", "to": "CW", "amount": 1909715, "time": "24/10/18 14:37:20", "block": -1}, {"status": "VALID", "from": "CU", "to": "W", "amount": 14569, "time": "24/10/18 14:39:39", "block": 260}, {"status": "VALID", "from": "CM", "to": "AJ", "amount": 3438689, "time": "24/10/18 14:40:51", "block": 280}, {"status": "VALID", "from": "BL", "to": "BU", "amount": 519065, "time": "24/10/18 14:41:44", "block": 280}, {"status": "VALID", "from": "CF", "to": "AD", "amount": 224857, "time": "24/10/18 14:43:19", "block": 280}, {"status": "VALID", "from": "Z", "to": "AR", "amount": 1226486, "time": "24/10/18 14:44:44", "block": 280}, {"status": "VALID", "from": "AL", "to": "CM", "amount": 1035842, "time": "24/10/18 14:45:05", "block": 280}, {"status": "UNRECORDED", "from": "AV", "to": "DE", "amount": 1268438, "time": "24/10/18 14:45:49", "block": 280}, {"status": "INVALID", "from": "AZ", "to": "CI", "amount": 2415761, "time": "24/10/18 14:46:09", "block": -1}, {"status": "INVALID", "from": "BQ", "to": "P", "amount": 17480916, "time": "24/10/18 14:46:16", "block": -1}, {"status": "VALID", "from": "AF", "to": "BU", "amount": 43058, "time": "24/10/18 14:46:55", "block": 280}, {"status": "INVALID", "from": "DC", "to": "CF", "amount": 234837, "time": "24/10/18 14:47:15", "block": -1}, {"status": "VALID", "from": "AR", "to": "BI", "amount": 6589515, "time": "24/10/18 14:48:58", "block": 280}, {"status": "INVALID", "from": "BX", "to": "J", "amount": 18502620, "time": "24/10/18 14:49:58", "block": -1}, {"status": "VALID", "from": "AC", "to": "BS", "amount": 55503, "time": "24/10/18 14:50:29", "block": 280}, {"status": "VALID", "from": "U", "to": "I", "amount": 138598, "time": "24/10/18 14:51:49", "block": 280}, {"status": "VALID", "from": "K", "to": "BX", "amount": 843089, "time": "24/10/18 14:52:57", "block": 280}, {"status": "VALID", "from": "I", "to": "CC", "amount": 7765935, "time": "24/10/18 14:54:11", "block": 280}, {"status": "VALID", "from": "V", "to": "BB", "amount": 248725, "time": "24/10/18 14:54:59", "block": 280}, {"status": "VALID", "from": "AP", "to": "D", "amount": 16082802, "time": "24/10/18 14:56:16", "block": 280}, {"status": "VALID", "from": "BR", "to": "Q", "amount": 3164920, "time": "24/10/18 14:57:50", "block": 280}, {"status": "INVALID", "from": "AT", "to": "CU", "amount": 431967, "time": "24/10/18 14:59:40", "block": -1}]